PIC16F84A_aalto/PIC16F84A/vhdl/ex07/stack.vhd
    --Push and pop should not be asserted simultaneously (push takes precedence in this implementation)

    --The stack pointer is not directly readable or writable as per requirements

    --PCLATH handling would need to be implemented separately in the calling unit

    --The output always reflects the top of the stack (most recently pushed value)



library IEEE;
use IEEE.STD_LOGIC_1164.ALL;
use IEEE.NUMERIC_STD.ALL;

entity stack_8x13 is
    Port (
        clk         : in  STD_LOGIC;
        reset       : in  STD_LOGIC;
        push        : in  STD_LOGIC;  -- Active high to push to stack
        pop         : in  STD_LOGIC;  -- Active high to pop from stack
        data_in     : in  STD_LOGIC_VECTOR(12 downto 0);  -- 13-bit input
        data_out    : out STD_LOGIC_VECTOR(12 downto 0);  -- 13-bit output
        stack_full  : out STD_LOGIC;  -- Indicates stack is full (8 levels)
        stack_empty : out STD_LOGIC   -- Indicates stack is empty
    );
end stack_8x13;

architecture Behavioral of stack_8x13 is
    type stack_type is array (0 to 7) of STD_LOGIC_VECTOR(12 downto 0);
    signal stack : stack_type := (others => (others => '0'));
    
    signal stack_ptr : integer range 0 to 7 := 0;
    signal count : integer range 0 to 8 := 0;
begin

    process(clk, reset)
    begin
        if reset = '1' then
            stack <= (others => (others => '0'));
            stack_ptr <= 0;
            count <= 0;
            stack_full <= '0';
            stack_empty <= '1';
        elsif rising_edge(clk) then
            -- Push operation takes precedence over pop if both are asserted
            if push = '1' then
                -- Store the input data at current pointer position
                stack(stack_ptr) <= data_in;
                
                -- Circular buffer behavior - overwrite oldest when full
                if count < 8 then
                    count <= count + 1;
                end if;
                
                -- Move pointer (circular)
                if stack_ptr = 7 then
                    stack_ptr <= 0;
                else
                    stack_ptr <= stack_ptr + 1;
                end if;
                
                stack_empty <= '0';
                if count = 7 then --stack is going to be full (count will be 8 at end of process)
                    stack_full <= '1';
                end if;
                
            elsif pop = '1' and count > 0 then
                -- For pop, we need to move pointer back first
                if stack_ptr = 0 then
                    stack_ptr <= 7;
                else
                    stack_ptr <= stack_ptr - 1;
                end if;
                
                count <= count - 1;
                
                stack_full <= '0';
                if count = 1 then
                    stack_empty <= '1';
                end if;
            end if;
        end if;
    end process;

    -- The output always shows the most recently pushed value (top of stack)
    data_out <= stack(7) when stack_ptr = 0 else stack(stack_ptr - 1);

end Behavioral;

PIC16F84A_aalto/exercise_project/vhdl/ex07/tb_ex07.vhd
library IEEE;
use IEEE.STD_LOGIC_1164.ALL;
use IEEE.NUMERIC_STD.ALL;
use IEEE.STD_LOGIC_TEXTIO.ALL;
use STD.TEXTIO.ALL;

entity tb_ex07 is
end tb_ex07;

architecture Behavioral of tb_ex07 is
    component stack_8x13
        Port (
            clk         : in  STD_LOGIC;
            reset       : in  STD_LOGIC;
            push        : in  STD_LOGIC;
            pop         : in  STD_LOGIC;
            data_in     : in  STD_LOGIC_VECTOR(12 downto 0);
            data_out    : out STD_LOGIC_VECTOR(12 downto 0);
            stack_full  : out STD_LOGIC;
            stack_empty : out STD_LOGIC
        );
    end component;

    signal clk          : STD_LOGIC := '0';
    signal reset        : STD_LOGIC := '1';
    signal push         : STD_LOGIC := '0';
    signal pop          : STD_LOGIC := '0';
    signal data_in      : STD_LOGIC_VECTOR(12 downto 0) := (others => '0');
    signal data_out     : STD_LOGIC_VECTOR(12 downto 0);
    signal stack_full   : STD_LOGIC;
    signal stack_empty  : STD_LOGIC;

    signal test_complete : boolean := false;
    
    constant CLK_PERIOD : time := 10 ns;
begin

    uut: stack_8x13 port map (
        clk => clk,
        reset => reset,
        push => push,
        pop => pop,
        data_in => data_in,
        data_out => data_out,
        stack_full => stack_full,
        stack_empty => stack_empty
    );
    
  

  -- Clock generator
    clk_process: process
    begin
        while not test_complete loop
            clk <= '0';
            wait for CLK_PERIOD/2;
            clk <= '1';
            wait for CLK_PERIOD/2;
        end loop;
        wait;
    end process;


    stimulus: process
        procedure push_value(val : in integer) is
        begin
            data_in <= std_logic_vector(to_unsigned(val, 13));
            push <= '1';
            wait for CLK_PERIOD;
            push <= '0';
            wait for CLK_PERIOD;
        end procedure;
        
        procedure pop_value is
        begin
            pop <= '1';
            wait for CLK_PERIOD;
            pop <= '0';
            wait for CLK_PERIOD;
        end procedure;
    begin
        -- Initial reset
        reset <= '1';
        wait for CLK_PERIOD*2;
        reset <= '0';
        wait for CLK_PERIOD;
        
        -- Test 1: Simple push and pop
        report "Test 1: Simple push and pop";
        push_value(1);
        assert stack_empty = '0' report "Stack should not be empty" severity error;
        pop_value;
        assert stack_empty = '1' report "Stack should be empty" severity error;
        
        -- Test 2: Fill the stack completely
        report "Test 2: Fill stack completely";
        for i in 1 to 8 loop
            push_value(i);
            assert to_integer(unsigned(data_out)) = i report "Top of stack incorrect" severity error;
        end loop;
        assert stack_full = '1' report "Stack should be full" severity error;
        
        -- Test 3: Overflow (9th push should wrap around)
        report "Test 3: Overflow test";
        push_value(9);
        assert stack_full = '1' report "Stack should remain full" severity error;
        
        -- Test 4: Pop all values
        report "Test 4: Empty the stack";
        for i in 1 to 8 loop
            pop_value;
        end loop;
        assert stack_empty = '1' report "Stack should be empty" severity error;
        
        -- Test 5: Mixed push/pop operations
        report "Test 5: Mixed operations";
        push_value(10);
        push_value(20);
        pop_value;
        push_value(30);
        push_value(40);
        pop_value;
        pop_value;
        assert to_integer(unsigned(data_out)) = 10 report "Top of stack incorrect" severity error;
        
        -- Test 6: Reset test
        report "Test 6: Reset test";
        push_value(100);
        push_value(200);
        reset <= '1';
        wait for CLK_PERIOD;
        reset <= '0';
        wait for CLK_PERIOD;
        assert stack_empty = '1' report "Stack should be empty after reset" severity error;
        
        report "All tests completed";
        test_complete <= true;
        wait;
    end process;


end Behavioral;

PIC16F84A_aalto/exercise_project/simulations/ex07/work/tb_ex07.vcd
$date
  Mon Apr  7 16:05:28 2025
$end
$version
  GHDL v0
$end
$timescale
  1 fs
$end
$scope module standard $end
$upscope $end
$scope module textio $end
$upscope $end
$scope module std_logic_1164 $end
$upscope $end
$scope module numeric_std $end
$upscope $end
$scope module std_logic_textio $end
$upscope $end
$scope module tb_ex07 $end
$var reg 1 ! clk $end
$var reg 1 " reset $end
$var reg 1 # push $end
$var reg 1 $ pop $end
$var reg 13 % data_in[12:0] $end
$var reg 13 & data_out[12:0] $end
$var reg 1 ' stack_full $end
$var reg 1 ( stack_empty $end
$var reg 1 ) test_complete $end
$scope module uut $end
$var reg 1 * clk $end
$var reg 1 + reset $end
$var reg 1 , push $end
$var reg 1 - pop $end
$var reg 13 . data_in[12:0] $end
$var reg 13 / data_out[12:0] $end
$var reg 1 0 stack_full $end
$var reg 1 1 stack_empty $end
$comment stack is not handled $end
$var integer 32 2 stack_ptr $end
$var integer 32 3 count $end
$upscope $end
$upscope $end
$enddefinitions $end
#0
0!
1"
0#
0$
b0000000000000 %
b0000000000000 &
0'
1(
0)
0*
1+
0,
0-
b0000000000000 .
b0000000000000 /
00
11
b0 2
b0 3
#5000000
1!
1*
#10000000
0!
0*
#15000000
1!
1*
#20000000
0!
0"
0*
0+
#25000000
1!
1*
#30000000
0!
1#
b0000000000001 %
0*
1,
b0000000000001 .
#35000000
1!
b0000000000001 &
0(
1*
b0000000000001 /
01
b1 2
b1 3
#40000000
0!
0#
0*
0,
#45000000
1!
1*
#50000000
0!
1$
0*
1-
#55000000
1!
b0000000000000 &
1(
1*
b0000000000000 /
11
b0 2
b0 3
#60000000
0!
0$
0*
0-
#65000000
1!
1*
#70000000
0!
1#
0*
1,
#75000000
1!
b0000000000001 &
0(
1*
b0000000000001 /
01
b1 2
b1 3
#80000000
0!
0#
0*
0,
#85000000
1!
1*
#90000000
0!
1#
b0000000000010 %
0*
1,
b0000000000010 .
#95000000
1!
b0000000000010 &
1*
b0000000000010 /
b10 2
b10 3
#100000000
0!
0#
0*
0,
#105000000
1!
1*
#110000000
0!
1#
b0000000000011 %
0*
1,
b0000000000011 .
#115000000
1!
b0000000000011 &
1*
b0000000000011 /
b11 2
b11 3
#120000000
0!
0#
0*
0,
#125000000
1!
1*
#130000000
0!
1#
b0000000000100 %
0*
1,
b0000000000100 .
#135000000
1!
b0000000000100 &
1*
b0000000000100 /
b100 2
b100 3
#140000000
0!
0#
0*
0,
#145000000
1!
1*
#150000000
0!
1#
b0000000000101 %
0*
1,
b0000000000101 .
#155000000
1!
b0000000000101 &
1*
b0000000000101 /
b101 2
b101 3
#160000000
0!
0#
0*
0,
#165000000
1!
1*
#170000000
0!
1#
b0000000000110 %
0*
1,
b0000000000110 .
#175000000
1!
b0000000000110 &
1*
b0000000000110 /
b110 2
b110 3
#180000000
0!
0#
0*
0,
#185000000
1!
1*
#190000000
0!
1#
b0000000000111 %
0*
1,
b0000000000111 .
#195000000
1!
b0000000000111 &
1*
b0000000000111 /
b111 2
b111 3
#200000000
0!
0#
0*
0,
#205000000
1!
1*
#210000000
0!
1#
b0000000001000 %
0*
1,
b0000000001000 .
#215000000
1!
b0000000001000 &
1'
1*
b0000000001000 /
10
b0 2
b1000 3
#220000000
0!
0#
0*
0,
#225000000
1!
1*
#230000000
0!
1#
b0000000001001 %
0*
1,
b0000000001001 .
#235000000
1!
b0000000001001 &
1*
b0000000001001 /
b1 2
#240000000
0!
0#
0*
0,
#245000000
1!
1*
#250000000
0!
1$
0*
1-
#255000000
1!
b0000000001000 &
0'
1*
b0000000001000 /
00
b0 2
b111 3
#260000000
0!
0$
0*
0-
#265000000
1!
1*
#270000000
0!
1$
0*
1-
#275000000
1!
b0000000000111 &
1*
b0000000000111 /
b111 2
b110 3
#280000000
0!
0$
0*
0-
#285000000
1!
1*
#290000000
0!
1$
0*
1-
#295000000
1!
b0000000000110 &
1*
b0000000000110 /
b110 2
b101 3
#300000000
0!
0$
0*
0-
#305000000
1!
1*
#310000000
0!
1$
0*
1-
#315000000
1!
b0000000000101 &
1*
b0000000000101 /
b101 2
b100 3
#320000000
0!
0$
0*
0-
#325000000
1!
1*
#330000000
0!
1$
0*
1-
#335000000
1!
b0000000000100 &
1*
b0000000000100 /
b100 2
b11 3
#340000000
0!
0$
0*
0-
#345000000
1!
1*
#350000000
0!
1$
0*
1-
#355000000
1!
b0000000000011 &
1*
b0000000000011 /
b11 2
b10 3
#360000000
0!
0$
0*
0-
#365000000
1!
1*
#370000000
0!
1$
0*
1-
#375000000
1!
b0000000000010 &
1*
b0000000000010 /
b10 2
b1 3
#380000000
0!
0$
0*
0-
#385000000
1!
1*
#390000000
0!
1$
0*
1-
#395000000
1!
b0000000001001 &
1(
1*
b0000000001001 /
11
b1 2
b0 3
#400000000
0!
0$
0*
0-
#405000000
1!
1*
#410000000
0!
1#
b0000000001010 %
0*
1,
b0000000001010 .
#415000000
1!
b0000000001010 &
0(
1*
b0000000001010 /
01
b10 2
b1 3
#420000000
0!
0#
0*
0,
#425000000
1!
1*
#430000000
0!
1#
b0000000010100 %
0*
1,
b0000000010100 .
#435000000
1!
b0000000010100 &
1*
b0000000010100 /
b11 2
b10 3
#440000000
0!
0#
0*
0,
#445000000
1!
1*
#450000000
0!
1$
0*
1-
#455000000
1!
b0000000001010 &
1*
b0000000001010 /
b10 2
b1 3
#460000000
0!
0$
0*
0-
#465000000
1!
1*
#470000000
0!
1#
b0000000011110 %
0*
1,
b0000000011110 .
#475000000
1!
b0000000011110 &
1*
b0000000011110 /
b11 2
b10 3
#480000000
0!
0#
0*
0,
#485000000
1!
1*
#490000000
0!
1#
b0000000101000 %
0*
1,
b0000000101000 .
#495000000
1!
b0000000101000 &
1*
b0000000101000 /
b100 2
b11 3
#500000000
0!
0#
0*
0,
#505000000
1!
1*
#510000000
0!
1$
0*
1-
#515000000
1!
b0000000011110 &
1*
b0000000011110 /
b11 2
b10 3
#520000000
0!
0$
0*
0-
#525000000
1!
1*
#530000000
0!
1$
0*
1-
#535000000
1!
b0000000001010 &
1*
b0000000001010 /
b10 2
b1 3
#540000000
0!
0$
0*
0-
#545000000
1!
1*
#550000000
0!
1#
b0000001100100 %
0*
1,
b0000001100100 .
#555000000
1!
b0000001100100 &
1*
b0000001100100 /
b11 2
b10 3
#560000000
0!
0#
0*
0,
#565000000
1!
1*
#570000000
0!
1#
b0000011001000 %
0*
1,
b0000011001000 .
#575000000
1!
b0000011001000 &
1*
b0000011001000 /
b100 2
b11 3
#580000000
0!
0#
0*
0,
#585000000
1!
1*
#590000000
0!
1"
b0000000000000 &
1(
0*
1+
b0000000000000 /
11
b0 2
b0 3
#595000000
1!
1*
#600000000
0!
0"
0*
0+
#605000000
1!
1*
#610000000
0!
1)
0*
