PIC16F84A_aalto/PIC16F84A/vhdl/ex05/memory.vhd
library IEEE;
use IEEE.STD_LOGIC_1164.ALL;
use IEEE.NUMERIC_STD.ALL;

entity memory is 
    generic (
        ADDR_WIDTH : integer := 8; 
        DATA_WIDTH : integer := 8
    );
    port (
        clk, rst : in std_logic;
        write_addr : in std_logic_vector(ADDR_WIDTH-1 downto 0);
        read_addr : in std_logic_vector(ADDR_WIDTH-1 downto 0);
        data_in : in std_logic_vector(DATA_WIDTH-1 downto 0);
        data_out : out std_logic_vector(DATA_WIDTH-1 downto 0);
        write_en, read_en : in std_logic;
        mem_status_in : in std_logic_vector(2 downto 0); -- alu_status_out
        mem_status_out : out std_logic_vector(2 downto 0) -- alu status_in
    ); 
end entity memory; 

architecture behavior of memory is 
    -- Signal declarations 
    type memory_array is array (0 to 2**ADDR_WIDTH-1) of std_logic_vector(DATA_WIDTH-1 downto 0);
    signal mem : memory_array := (others => (others => '0'));  -- memory initialization
    constant STATUS_ADDR: std_logic_vector(ADDR_WIDTH-1 downto 0) := 
        std_logic_vector(to_unsigned(3, ADDR_WIDTH));
    
    -- Registered output for better timing
    signal data_out_reg : std_logic_vector(DATA_WIDTH-1 downto 0) := (others => '0');

begin 
    -- Status output is continuously driven from memory location 0x03
    mem_status_out <= mem(to_integer(unsigned(STATUS_ADDR)))(2 downto 0);

    -- Synchronous memory operations
    process (clk) 
    begin 
        if rising_edge(clk) then
            if rst = '1' then 
                -- Reset clears entire memory and output
                mem <= (others => (others => '0'));
                data_out_reg <= (others => '0');
            else
                -- Write operation (has priority if both read and write enabled)
                if write_en = '1' then 
                    if write_addr = STATUS_ADDR then
                        -- Direct write to status register
                        mem(to_integer(unsigned(write_addr))) <= data_in; 
                    else
                        -- Normal write with automatic status update
                        mem(to_integer(unsigned(write_addr))) <= data_in;
                        -- Update status register (bits 2-0 only)
                        mem(to_integer(unsigned(STATUS_ADDR))) <= 
                            (DATA_WIDTH-1 downto 3 => '0') & mem_status_in; 
                    end if;
                end if;
                
                -- Read operation (registered output)
                if read_en = '1' then
                    data_out_reg <= mem(to_integer(unsigned(read_addr)));
                end if;
            end if;
        end if;
    end process; 

    -- Drive output from register
    data_out <= data_out_reg;
    
end architecture behavior;

PIC16F84A_aalto/PIC16F84A/vhdl/project/full_adder.vhd
library IEEE;
use IEEE.STD_LOGIC_1164.ALL;


entity full_adder is 
	port (
		A, B, CI : in std_logic;
		S, CO : out std_logic
		);
	
end full_adder;

architecture behavior of full_adder is
	begin
		process(A, B, CI)
		begin
			S <= A xor B xor CI;
			CO <= (A and B) or (CI and (A or B));
		end process;
end architecture behavior;

PIC16F84A_aalto/PIC16F84A/vhdl/ex04/Nbit_ripple_carry_adder.vhd
LIBRARY ieee;
USE ieee.std_logic_1164.ALL;


entity Nbit_ripple_carry_adder is
	generic (
		N : integer := 8
		);
	port (
		A, B : in std_logic_vector (N-1 downto 0);
		S : out std_logic_vector (N-1 downto 0);
		CO : out std_logic
		);
end entity Nbit_ripple_carry_adder;

architecture structural of Nbit_ripple_carry_adder is

 -- Component declaration for the full adder
    component full_adder
        port (
            A    : in  std_logic;
            B    : in  std_logic;
            CI  : in  std_logic;
            S    : out std_logic;
            CO : out std_logic
        );
    end component;

	signal carry : std_logic_vector(N downto 0);

begin
	carry(0) <= '0';
	GEN_ADDERS: for i in 0 to N-1 generate
		FA: entity work.full_adder
		port map (
			A => A(i),
			B => B(i),
			CI => carry(i),
			S => S(i),
			CO => carry(i+1)
		);
	end generate GEN_ADDERS;
	CO <= carry(N);

end architecture structural;

PIC16F84A_aalto/exercise_project/vhdl/ex04/alu.vhd
library IEEE;
use IEEE.STD_LOGIC_1164.ALL;
use IEEE.NUMERIC_STD.ALL;
use STD.TEXTIO.ALL;
use work.ALU_Types.ALL;

-- ADD for both ADDWF and ADDLW
-- AND2 for both ANDWF and ANDLW
-- IOR for both IORWF and IORLW
-- SUB for both SUBWF and SUBLW
-- XOR2 for both XORWF and XORLW

entity alu is 
	port (
		A, B : in std_logic_vector(7 downto 0);
		operation : in ALU_operation;              
		result : out std_logic_vector(7 downto 0);
		bit_select : in std_logic_vector(2 downto 0);
		status_in : in std_logic_vector(2 downto 0);
		status : out std_logic_vector(2 downto 0)
		);
end entity alu;

architecture behavior of alu is 

	--Constant declarations
	constant N : integer := 8;  -- 8-bit adder
	
	-- Component declarations
	component Nbit_ripple_carry_adder is
 	       port (
           	 A  : in  std_logic_vector(N-1 downto 0);
           	 B  : in  std_logic_vector(N-1 downto 0);
           	 S  : out std_logic_vector(N-1 downto 0);
           	 CO : out std_logic
       		 );
    	end component;

	-- Signals used for calculations
	signal temp_result : std_logic_vector(8 downto 0);
	signal B_2complement : std_logic_vector(7 downto 0);
	signal clear_mask : std_logic_vector(7 downto 0);
	signal update_Zflag : std_logic;
    signal adder_result : std_logic_vector (7 downto 0);
    signal adder_CO : std_logic;
    signal sub_result : std_logic_vector(7 downto 0);
    signal sub_CO : std_logic;

begin
     --status <= status_in; 
     ADDER_INSTANCE: Nbit_ripple_carry_adder
        				port map (A  => A, B  => B, S  => adder_result, CO => adder_CO);

     B_2complement <=  std_logic_vector(unsigned(not B) +1);
      
     SUBSTRACTOR_INSTANCE :  Nbit_ripple_carry_adder
        				port map (A  => A, B => B_2complement, S  => sub_result, CO => sub_CO);

     clear_mask <= 
    (others => '1') when operation /= BCF and operation /= BSF else  -- Default case
    (0 => '0', others => '1') when operation = BCF and bit_select = "000" else
    (1 => '0', others => '1') when operation = BCF and bit_select = "001" else
    (2 => '0', others => '1') when operation = BCF and bit_select = "010" else
    (3 => '0', others => '1') when operation = BCF and bit_select = "011" else
    (4 => '0', others => '1') when operation = BCF and bit_select = "100" else
    (5 => '0', others => '1') when operation = BCF and bit_select = "101" else
    (6 => '0', others => '1') when operation = BCF and bit_select = "110" else
    (7 => '0', others => '1') when operation = BCF and bit_select = "111" else
    (others => '1') when operation = BCF else  -- Default for BCF
    (0 => '1', others => '0') when operation = BSF and bit_select = "000" else
    (1 => '1', others => '0') when operation = BSF and bit_select = "001" else
    (2 => '1', others => '0') when operation = BSF and bit_select = "010" else
    (3 => '1', others => '0') when operation = BSF and bit_select = "011" else
    (4 => '1', others => '0') when operation = BSF and bit_select = "100" else
    (5 => '1', others => '0') when operation = BSF and bit_select = "101" else
    (6 => '1', others => '0') when operation = BSF and bit_select = "110" else
    (7 => '1', others => '0') when operation = BSF and bit_select = "111" else
    (others => '0') when operation = BSF else  -- Default for BSF
    (others => '1');  -- Fallback default

    --process for taking care of result and Z_flag
	process(A, B, operation, bit_select, status_in, adder_result, sub_result, clear_mask)
	begin   
		case operation is
			when ADD =>    
                    result <= adder_result;
  					update_Zflag <= '1';

			when AND2 =>     
				result <= A and B; 
				update_Zflag <= '1';

			when COMF => 
				result <= not A;
				update_Zflag <= '1';
				
			when DECF =>
				result <= std_logic_vector(unsigned(A) - 1);
				update_Zflag <= '1';

			when INCF => 
				result <= std_logic_vector(unsigned(A) + 1);
				update_Zflag <= '1';

			when IOR => 
				result <= A or B;
				update_Zflag <= '1';

			when RLF =>
				result <= A(6 downto 0) & status_in(0);
				update_Zflag <= '0';

			when RRF =>
				result <= status_in(0) & A(7 downto 1);
				update_Zflag <= '0';

			when SUB =>
				result <= sub_result; 
				update_Zflag <= '1';

			when SWAPF =>
				result <= A(3 downto 0) & A(7 downto 4);
				update_Zflag <= '0';

			when XOR2 =>
				result <= A xor B;
				update_Zflag <= '1';

			when CLRF =>  --clear f
				result <= "00000000"; 
				update_Zflag <= '1';

			when CLEARW => --clear W
				result <= "00000000";
				update_Zflag <= '1';

			when MOVF => --move f
				result <= A; --in result, I put what I have to move 
				update_Zflag <= '1';

			when MOVWF => --move (W) to (f)
				result <= A;
				update_Zflag <= '0';

			when MOVLW => --move literal k to (W)
				result <= A;
				update_Zflag <= '0';

			when BCF =>
				result <= A and clear_mask;
				update_Zflag <= '0';

			when BSF =>
				result <= A or clear_mask;
				update_Zflag <= '0';

            when NOP =>
                 result <= "00000000";       
	        end case;
     end process;

        --process for taking care of status
		process(result, update_Zflag, status_in, operation, adder_CO, sub_CO)
    			begin
                    status <= status_in; 
       				if update_Zflag = '1' then
            				if result = "00000000" then
                				status(2) <= '1';  -- Set Z flag if result is zero
            				else
                				status(2) <= '0';  -- Clear Z flag if result is non-zero
            				end if;
        			end if;

                    if operation = ADD then
                        status(0) <= adder_CO;
					    status(1) <= A(3) and B(3); --carry_out_4bit
                    elsif operation = SUB then
                         status(0) <= sub_CO;
				         status(1) <= A(3) and B_2complement(3);
                     elsif operation = RLF then 
                        status(0) <= A(7);
                     elsif operation = RRF then 
                        status(0) <= A(0);
                     elsif operation = NOP then 
                         status <= "000";
                     end if;

    	end process;

      
end architecture behavior;

PIC16F84A_aalto/PIC16F84A/vhdl/ex05/tb_ex05.vhd
library IEEE;
use IEEE.STD_LOGIC_1164.ALL;
use IEEE.NUMERIC_STD.ALL;
use work.ALU_Types.ALL;

entity tb_ex05 is
end tb_ex05;

architecture behavior of tb_ex05 is
    -- Constants
    constant CLK_PERIOD : time := 10 ns;
    
    -- ALU signals
    signal alu_A, alu_B, alu_result : std_logic_vector(7 downto 0);
    signal operation : ALU_operation;
    signal alu_bit_select : std_logic_vector(2 downto 0) := "000";
    signal alu_status_in, alu_status_out : std_logic_vector(2 downto 0);
    
    -- Memory signals
    signal clk, rst : std_logic := '0';
    signal mem_write_addr, mem_read_addr : std_logic_vector(7 downto 0);
    signal mem_data_in, mem_data_out : std_logic_vector(7 downto 0);
    signal mem_write_en, mem_read_en : std_logic;
    
    -- Test control
    signal test_complete : boolean := false;
    
begin
    -- Instantiate ALU
    uut_alu: entity work.alu
    port map (
        A => alu_A,
        B => alu_B,
        operation => operation,
        result => alu_result,
        bit_select => alu_bit_select,
        status_in => alu_status_in,
        status => alu_status_out
    );
    
    -- Instantiate Memory
    uut_mem: entity work.memory
    generic map (
        ADDR_WIDTH => 8,
        DATA_WIDTH => 8
    )
    port map (
        clk => clk,
        rst => rst,
        write_addr => mem_write_addr,
        read_addr => mem_read_addr,
        data_in => mem_data_in,
        data_out => mem_data_out,
        write_en => mem_write_en,
        read_en => mem_read_en,
        mem_status_in => alu_status_out, --branching between two modules
        mem_status_out => alu_status_in
    );
       

    -- Clock generator
    clk_process: process
    begin
        while not test_complete loop
            clk <= '0';
            wait for CLK_PERIOD/2;
            clk <= '1';
            wait for CLK_PERIOD/2;
        end loop;
        wait;
    end process;
    
    -- Stimulus process
    stim_proc: process
    begin
        -- Initialize
        rst <= '1';
        mem_write_en <= '0';
        mem_read_en <= '0';
        operation <= NOP;
        wait for CLK_PERIOD*2;
        rst <= '0';
        wait for CLK_PERIOD/2;
        
        -- Test 1: Write value to memory
        report "Writing 0x55 to address 0x10";
        mem_write_addr <= x"10";
        mem_data_in <= x"55";
        mem_write_en <= '1';
        wait for CLK_PERIOD;
        mem_write_en <= '0';
       -- wait for CLK_PERIOD;
        
        -- Test 2: Read value back from memory
        report "Reading from address 0x10";
        mem_read_addr <= x"10";
        mem_read_en <= '1';
        wait for CLK_PERIOD;
        mem_read_en <= '0';
       -- wait for CLK_PERIOD;
        
        -- Test 3: Perform ADD operation (5 + 3)
        report "Testing ADD operation (5 + 3)";
        -- Write first operand to memory
        mem_write_addr <= x"20";
        mem_data_in <= x"05";
        mem_write_en <= '1';
        wait for CLK_PERIOD;
        mem_write_en <= '0';
       -- wait for CLK_PERIOD;
        
               
        -- Read operand from memory
        mem_read_addr <= x"20";
        mem_read_en <= '1';
        wait for CLK_PERIOD;
        alu_A <= mem_data_out;  -- Feed to ALU
        alu_B <= x"03";
        operation <= ADD;
        mem_read_en <= '0';
        
        -- Write result to memory
        wait for CLK_PERIOD/2;
        mem_write_addr <= x"30";
        mem_data_in <= alu_result;
        mem_write_en <= '1';
        wait for CLK_PERIOD;
        mem_write_en <= '0';
       -- wait for CLK_PERIOD;
        
        -- Verify result
        mem_read_addr <= x"30";
        mem_read_en <= '1';
        wait for CLK_PERIOD;
        mem_read_en <= '0';
        wait for CLK_PERIOD;
        
   
       -- Test 4: Perform AND
        report "Testing AND";
        -- Write first operand to memory
        mem_write_addr <= x"40";
        mem_data_in <= x"FA";
        mem_write_en <= '1';
        wait for CLK_PERIOD;
        mem_write_en <= '0';
       -- wait for CLK_PERIOD;
        
               
        -- Read operand from memory
        mem_read_addr <= x"40";
        mem_read_en <= '1';
        wait for CLK_PERIOD;
        alu_A <= mem_data_out;  -- Feed to ALU
        alu_B <= x"07";
        operation <= AND2;
        mem_read_en <= '0';
        
        -- Write result to memory
        wait for CLK_PERIOD/2;
        mem_write_addr <= x"60";
        mem_data_in <= alu_result;
        mem_write_en <= '1';
        wait for CLK_PERIOD;
        mem_write_en <= '0';
       -- wait for CLK_PERIOD;
        
        -- Verify result
        mem_read_addr <= x"60";
        mem_read_en <= '1';
        wait for CLK_PERIOD;
        mem_read_en <= '0';
        wait for CLK_PERIOD;

        -- Test 5: Perform AND equal to 0 and check status...
        report "Testing AND and status";
        -- Write first operand to memory
        mem_write_addr <= x"AB";
        mem_data_in <= x"AA";
        mem_write_en <= '1';
        wait for CLK_PERIOD;
        mem_write_en <= '0';
       -- wait for CLK_PERIOD;
        
               
        -- Read operand from memory
        mem_read_addr <= x"AB";
        mem_read_en <= '1';
        wait for CLK_PERIOD;
        alu_A <= mem_data_out;  -- Feed to ALU
        alu_B <= x"00";
        operation <= AND2;
        mem_read_en <= '0';
        
        -- Write result to memory
        wait for CLK_PERIOD/2;
        mem_write_addr <= x"60";
        mem_data_in <= alu_result;
        mem_write_en <= '1';
        wait for CLK_PERIOD;
        mem_write_en <= '0';
       -- wait for CLK_PERIOD;
        
        -- Verify result
        mem_read_addr <= x"60";
        mem_read_en <= '1';
        wait for CLK_PERIOD;
        mem_read_en <= '0';
        wait for CLK_PERIOD;

 
               
        -- Test complete
        report "All tests completed successfully";
        test_complete <= true;
        wait;
    end process;
    
end behavior;

PIC16F84A_aalto/exercise_project/simulations/ex05/work/tb_ex05.vcd
$date
  Thu Mar 27 18:54:25 2025
$end
$version
  GHDL v0
$end
$timescale
  1 fs
$end
$scope module standard $end
$upscope $end
$scope module textio $end
$upscope $end
$scope module std_logic_1164 $end
$upscope $end
$scope module numeric_std $end
$upscope $end
$scope module alu_types $end
$upscope $end
$scope module tb_ex05 $end
$var reg 8 ! alu_a[7:0] $end
$var reg 8 " alu_b[7:0] $end
$var reg 8 # alu_result[7:0] $end
$comment operation is not handled $end
$var reg 3 $ alu_bit_select[2:0] $end
$var reg 3 % alu_status_in[2:0] $end
$var reg 3 & alu_status_out[2:0] $end
$var reg 1 ' clk $end
$var reg 1 ( rst $end
$var reg 8 ) mem_write_addr[7:0] $end
$var reg 8 * mem_read_addr[7:0] $end
$var reg 8 + mem_data_in[7:0] $end
$var reg 8 , mem_data_out[7:0] $end
$var reg 1 - mem_write_en $end
$var reg 1 . mem_read_en $end
$var reg 1 / test_complete $end
$scope module uut_alu $end
$var reg 8 0 a[7:0] $end
$var reg 8 1 b[7:0] $end
$comment operation is not handled $end
$var reg 8 2 result[7:0] $end
$var reg 3 3 bit_select[2:0] $end
$var reg 3 4 status_in[2:0] $end
$var reg 3 5 status[2:0] $end
$var reg 9 6 temp_result[8:0] $end
$var reg 8 7 b_2complement[7:0] $end
$var reg 8 8 clear_mask[7:0] $end
$var reg 1 9 update_zflag $end
$var reg 8 : adder_result[7:0] $end
$var reg 1 ; adder_co $end
$var reg 8 < sub_result[7:0] $end
$var reg 1 = sub_co $end
$scope module adder_instance $end
$var reg 8 > a[7:0] $end
$var reg 8 ? b[7:0] $end
$var reg 8 @ s[7:0] $end
$var reg 1 A co $end
$var reg 9 B carry[8:0] $end
$scope module gen_adders(0) $end
$scope module fa $end
$var reg 1 C a $end
$var reg 1 D b $end
$var reg 1 E ci $end
$var reg 1 F s $end
$var reg 1 G co $end
$upscope $end
$upscope $end
$scope module gen_adders(1) $end
$scope module fa $end
$var reg 1 H a $end
$var reg 1 I b $end
$var reg 1 J ci $end
$var reg 1 K s $end
$var reg 1 L co $end
$upscope $end
$upscope $end
$scope module gen_adders(2) $end
$scope module fa $end
$var reg 1 M a $end
$var reg 1 N b $end
$var reg 1 O ci $end
$var reg 1 P s $end
$var reg 1 Q co $end
$upscope $end
$upscope $end
$scope module gen_adders(3) $end
$scope module fa $end
$var reg 1 R a $end
$var reg 1 S b $end
$var reg 1 T ci $end
$var reg 1 U s $end
$var reg 1 V co $end
$upscope $end
$upscope $end
$scope module gen_adders(4) $end
$scope module fa $end
$var reg 1 W a $end
$var reg 1 X b $end
$var reg 1 Y ci $end
$var reg 1 Z s $end
$var reg 1 [ co $end
$upscope $end
$upscope $end
$scope module gen_adders(5) $end
$scope module fa $end
$var reg 1 \ a $end
$var reg 1 ] b $end
$var reg 1 ^ ci $end
$var reg 1 _ s $end
$var reg 1 ` co $end
$upscope $end
$upscope $end
$scope module gen_adders(6) $end
$scope module fa $end
$var reg 1 a a $end
$var reg 1 b b $end
$var reg 1 c ci $end
$var reg 1 d s $end
$var reg 1 e co $end
$upscope $end
$upscope $end
$scope module gen_adders(7) $end
$scope module fa $end
$var reg 1 f a $end
$var reg 1 g b $end
$var reg 1 h ci $end
$var reg 1 i s $end
$var reg 1 j co $end
$upscope $end
$upscope $end
$upscope $end
$scope module substractor_instance $end
$var reg 8 k a[7:0] $end
$var reg 8 l b[7:0] $end
$var reg 8 m s[7:0] $end
$var reg 1 n co $end
$var reg 9 o carry[8:0] $end
$scope module gen_adders(0) $end
$scope module fa $end
$var reg 1 p a $end
$var reg 1 q b $end
$var reg 1 r ci $end
$var reg 1 s s $end
$var reg 1 t co $end
$upscope $end
$upscope $end
$scope module gen_adders(1) $end
$scope module fa $end
$var reg 1 u a $end
$var reg 1 v b $end
$var reg 1 w ci $end
$var reg 1 x s $end
$var reg 1 y co $end
$upscope $end
$upscope $end
$scope module gen_adders(2) $end
$scope module fa $end
$var reg 1 z a $end
$var reg 1 { b $end
$var reg 1 | ci $end
$var reg 1 } s $end
$var reg 1 !" co $end
$upscope $end
$upscope $end
$scope module gen_adders(3) $end
$scope module fa $end
$var reg 1 "" a $end
$var reg 1 #" b $end
$var reg 1 $" ci $end
$var reg 1 %" s $end
$var reg 1 &" co $end
$upscope $end
$upscope $end
$scope module gen_adders(4) $end
$scope module fa $end
$var reg 1 '" a $end
$var reg 1 (" b $end
$var reg 1 )" ci $end
$var reg 1 *" s $end
$var reg 1 +" co $end
$upscope $end
$upscope $end
$scope module gen_adders(5) $end
$scope module fa $end
$var reg 1 ," a $end
$var reg 1 -" b $end
$var reg 1 ." ci $end
$var reg 1 /" s $end
$var reg 1 0" co $end
$upscope $end
$upscope $end
$scope module gen_adders(6) $end
$scope module fa $end
$var reg 1 1" a $end
$var reg 1 2" b $end
$var reg 1 3" ci $end
$var reg 1 4" s $end
$var reg 1 5" co $end
$upscope $end
$upscope $end
$scope module gen_adders(7) $end
$scope module fa $end
$var reg 1 6" a $end
$var reg 1 7" b $end
$var reg 1 8" ci $end
$var reg 1 9" s $end
$var reg 1 :" co $end
$upscope $end
$upscope $end
$upscope $end
$upscope $end
$scope module uut_mem $end
$var reg 1 ;" clk $end
$var reg 1 <" rst $end
$var reg 8 =" write_addr[7:0] $end
$var reg 8 >" read_addr[7:0] $end
$var reg 8 ?" data_in[7:0] $end
$var reg 8 @" data_out[7:0] $end
$var reg 1 A" write_en $end
$var reg 1 B" read_en $end
$var reg 3 C" mem_status_in[2:0] $end
$var reg 3 D" mem_status_out[2:0] $end
$comment mem is not handled $end
$var reg 8 E" data_out_reg[7:0] $end
$upscope $end
$upscope $end
$enddefinitions $end
#0
bUUUUUUUU !
bUUUUUUUU "
b00000000 #
b000 $
b000 %
b000 &
0'
1(
bUUUUUUUU )
bUUUUUUUU *
bUUUUUUUU +
b00000000 ,
0-
0.
0/
bUUUUUUUU 0
bUUUUUUUU 1
b00000000 2
b000 3
b000 4
b000 5
bUUUUUUUUU 6
bXXXXXXXX 7
b11111111 8
19
bUUUUUUUU :
U;
bUUUUUUUU <
U=
bUUUUUUUU >
bUUUUUUUU ?
bUUUUUUUU @
UA
bUUUUUUUU0 B
UC
UD
0E
UF
UG
UH
UI
UJ
UK
UL
UM
UN
UO
UP
UQ
UR
US
UT
UU
UV
UW
UX
UY
UZ
U[
U\
U]
U^
U_
U`
Ua
Ub
Uc
Ud
Ue
Uf
Ug
Uh
Ui
Uj
bUUUUUUUU k
bXXXXXXXX l
bUUUUUUUU m
Un
bUUUUUUUU0 o
Up
Xq
0r
Us
Ut
Uu
Xv
Uw
Ux
Uy
Uz
X{
U|
U}
U!"
U""
X#"
U$"
U%"
U&"
U'"
X("
U)"
U*"
U+"
U,"
X-"
U."
U/"
U0"
U1"
X2"
U3"
U4"
U5"
U6"
X7"
U8"
U9"
U:"
0;"
1<"
bUUUUUUUU ="
bUUUUUUUU >"
bUUUUUUUU ?"
b00000000 @"
0A"
0B"
b000 C"
b000 D"
b00000000 E"
#5000000
1'
1;"
#10000000
0'
0;"
#15000000
1'
1;"
#20000000
0'
0(
0;"
0<"
#25000000
1'
b00010000 )
b01010101 +
1-
1;"
b00010000 ="
b01010101 ?"
1A"
#30000000
0'
0;"
#35000000
1'
b00010000 *
b01010101 ,
0-
1.
1;"
b00010000 >"
b01010101 @"
0A"
1B"
b01010101 E"
#40000000
0'
0;"
#45000000
1'
b00100000 )
b00000101 +
1-
0.
1;"
b00100000 ="
b00000101 ?"
1A"
0B"
#50000000
0'
0;"
#55000000
1'
b00100000 *
b00000101 ,
0-
1.
1;"
b00100000 >"
b00000101 @"
0A"
1B"
b00000101 E"
#60000000
0'
0;"
#65000000
b00000101 !
b00000011 "
b00001000 #
b000 &
1'
0.
b00000101 0
b00000011 1
b00001000 2
b000 5
b11111101 7
b00001000 :
0;
b00000010 <
1=
b00000101 >
b00000011 ?
b00001000 @
0A
b000001110 B
1C
1D
0F
1G
0H
1I
1J
0K
1L
1M
0N
1O
0P
1Q
0R
0S
1T
1U
0V
0W
0X
0Y
0Z
0[
0\
0]
0^
0_
0`
0a
0b
0c
0d
0e
0f
0g
0h
0i
0j
b00000101 k
b11111101 l
b00000010 m
1n
b111111010 o
1p
1q
0s
1t
0u
0v
1w
1x
0y
1z
1{
0|
0}
1!"
0""
1#"
1$"
0%"
1&"
0'"
1("
1)"
0*"
1+"
0,"
1-"
1."
0/"
10"
01"
12"
13"
04"
15"
06"
17"
18"
09"
1:"
1;"
0B"
b000 C"
#70000000
0'
b00110000 )
b00001000 +
1-
0;"
b00110000 ="
b00001000 ?"
1A"
#75000000
1'
1;"
#80000000
0'
b00110000 *
0-
1.
0;"
b00110000 >"
0A"
1B"
#85000000
1'
b00001000 ,
1;"
b00001000 @"
b00001000 E"
#90000000
0'
0.
0;"
0B"
#95000000
1'
1;"
#100000000
0'
b01000000 )
b11111010 +
1-
0;"
b01000000 ="
b11111010 ?"
1A"
#105000000
1'
1;"
#110000000
0'
b01000000 *
0-
1.
0;"
b01000000 >"
0A"
1B"
#115000000
1'
b11111010 ,
1;"
b11111010 @"
b11111010 E"
#120000000
b11111010 !
b00000111 "
b00000010 #
0'
0.
b11111010 0
b00000111 1
b00000010 2
b11111001 7
b00000001 :
1;
b11110011 <
b11111010 >
b00000111 ?
b00000001 @
1A
b111111100 B
0C
1F
0G
1H
0J
0K
0M
1N
1R
0U
1V
1W
1Y
0Z
1[
1\
1^
0_
1`
1a
1c
0d
1e
1f
1h
0i
1j
b11111010 k
b11111001 l
b11110011 m
b111110000 o
0p
1s
0t
1u
0w
1x
0y
0z
0{
0|
0}
0!"
1""
0$"
0%"
1'"
1*"
1,"
1/"
11"
14"
16"
19"
0;"
0B"
#125000000
1'
b01100000 )
b00000010 +
1-
1;"
b01100000 ="
b00000010 ?"
1A"
#130000000
0'
0;"
#135000000
1'
b01100000 *
b00000010 ,
0-
1.
1;"
b01100000 >"
b00000010 @"
0A"
1B"
b00000010 E"
#140000000
0'
0;"
#145000000
1'
0.
1;"
0B"
#150000000
0'
0;"
#155000000
1'
b10101011 )
b10101010 +
1-
1;"
b10101011 ="
b10101010 ?"
1A"
#160000000
0'
0;"
#165000000
1'
b10101011 *
b10101010 ,
0-
1.
1;"
b10101011 >"
b10101010 @"
0A"
1B"
b10101010 E"
#170000000
0'
0;"
#175000000
b10101010 !
b00000000 "
b00000000 #
b100 &
1'
0.
b10101010 0
b00000000 1
b00000000 2
b100 5
b00000000 7
b10101010 :
0;
b10101010 <
0=
b10101010 >
b00000000 ?
b10101010 @
0A
b000000000 B
0D
0F
0I
1K
0L
0N
0O
0P
0Q
0T
1U
0V
0W
0Y
0Z
0[
0^
1_
0`
0a
0c
0d
0e
0h
1i
0j
b10101010 k
b00000000 l
b10101010 m
0n
b000000000 o
0q
0s
0#"
1%"
0&"
0'"
0("
0)"
0*"
0+"
0-"
0."
1/"
00"
01"
02"
03"
04"
05"
07"
08"
19"
0:"
1;"
0B"
b100 C"
#180000000
0'
b01100000 )
b00000000 +
1-
0;"
b01100000 ="
b00000000 ?"
1A"
#185000000
b100 %
1'
b100 4
1;"
b100 D"
#190000000
0'
b01100000 *
0-
1.
0;"
b01100000 >"
0A"
1B"
#195000000
1'
b00000000 ,
1;"
b00000000 @"
b00000000 E"
#200000000
0'
0.
0;"
0B"
#205000000
1'
1;"
#210000000
0'
1/
0;"
